yuipybase/__init__.py
yuipybase/env.py
yuipybase/project.py
yuipybase-0.1.0.dist-info/METADATA
yuipybase-0.1.0.dist-info/WHEEL
yuipybase-0.1.0.dist-info/top_level.txt
yuipybase-0.1.0.dist-info/RECORD
