Metadata-Version: 2.4
Name: yuipybase
Version: 0.1.0
Summary: Python basic environment setup library
Home-page: https://github.com/FlandollScarlet495/pybase
Author: 結愛ちゃん
Classifier: Programming Language :: Python :: 3
Classifier: License :: OSI Approved :: MIT License
Classifier: Operating System :: OS Independent
Requires-Python: >=3.8
Dynamic: author
Dynamic: classifier
Dynamic: description
Dynamic: description-content-type
Dynamic: home-page
Dynamic: requires-python
Dynamic: summary
